__version__.py
arguments.py
common/__init__.py
common/utils.py
config.py
defectdojo/__init__.py
defectdojo/engagements.py
defectdojo/languages.py
defectdojo/product_api_scan.py
defectdojo/product_types.py
defectdojo/products.py
defectdojo/scans.py
defectdojo/test_types.py
defectdojo/tests.py
defectdojo/tool_configurations.py
http_client.py
importer/__init__.py
importer/execute.py
importer/findings.py
importer/importer.py
importer/languages.py
importer/validations.py
integrations/__init__.py
integrations/dtrack.py
models/__init__.py
models/api_scan_configuration.py
models/common.py
models/config.py
models/dtrack.py
models/engagement.py
models/exceptions.py
models/product.py
models/scan.py
models/tests.py
defectdojo_importer-0.0.4.dist-info/METADATA
defectdojo_importer-0.0.4.dist-info/WHEEL
defectdojo_importer-0.0.4.dist-info/entry_points.txt
defectdojo_importer-0.0.4.dist-info/licenses/LICENSE
defectdojo_importer-0.0.4.dist-info/RECORD
