Metadata-Version: 2.4
Name: defectdojo-importer
Version: 0.0.4
Summary: DefectDojo Importer Tool
License: Apache-2.0
License-File: LICENSE
Keywords: DefectDojo
Author: Azunna Ikonne
Author-email: ikonnea@gmail.com
Maintainer: Azunna Ikonne
Maintainer-email: ikonnea@gmail.com
Requires-Python: >=3.9,<4
Classifier: License :: OSI Approved :: Apache Software License
Classifier: Natural Language :: English
Classifier: Operating System :: OS Independent
Classifier: Programming Language :: Python :: 3
Classifier: Programming Language :: Python :: 3.9
Classifier: Programming Language :: Python :: 3.10
Classifier: Programming Language :: Python :: 3.11
Classifier: Programming Language :: Python :: 3.12
Classifier: Programming Language :: Python :: 3.13
Classifier: Programming Language :: Python :: 3.14
Requires-Dist: python-dotenv (>=1.1.1,<2.0.0)
Requires-Dist: requests (>=2.32.5,<3.0.0)
Project-URL: Repository, https://github.com/1azunna/defectdojo-importer
